CONTRIBUTORS.txt
MANIFEST.in
README.rst
requirements.txt
setup.py
tox.ini
gipsy/__init__.py
gipsy/sections/__init__.py
gipsy/sections/admin.py
gipsy/sections/admin_base.py
gipsy/sections/apps.py
gipsy/sections/forms.py
gipsy/sections/forms_base.py
gipsy/sections/managers.py
gipsy/sections/models.py
gipsy/sections/models_base.py
gipsy/sections/tests.py
gipsy/sections/views.py
gipsy/sections/migrations/0001_initial.py
gipsy/sections/migrations/0002_auto_20151004_2212.py
gipsy/sections/migrations/__init__.py
gipsy_sections.egg-info/PKG-INFO
gipsy_sections.egg-info/SOURCES.txt
gipsy_sections.egg-info/dependency_links.txt
gipsy_sections.egg-info/namespace_packages.txt
gipsy_sections.egg-info/pbr.json
gipsy_sections.egg-info/requires.txt
gipsy_sections.egg-info/top_level.txt
requirements/base.txt
requirements/dev.txt
requirements/production.txt
requirements/test.txt