Metadata-Version: 1.1
Name: gipsy-sections
Version: 0.4.1
Summary: Gipsy Sections
Home-page: http://github.com/revsquare/gipsy-sections
Author: Rafał Selewońko
Author-email: rafal@selewonko.com
License: MIT
Platform: UNKNOWN
Classifier: Operating System :: OS Independent
Classifier: Programming Language :: Python
Classifier: Programming Language :: Python :: 3
Classifier: Programming Language :: Python :: 3.2
Classifier: Programming Language :: Python :: 3.3
Classifier: Programming Language :: Python :: 3.4
Classifier: Topic :: Internet :: WWW/HTTP
